MolNotator/MGF_updater.py
MolNotator/__init__.py
MolNotator/adnotator.py
MolNotator/cosiner.py
MolNotator/dereplicator.py
MolNotator/duplicate_filter.py
MolNotator/fragnotator.py
MolNotator/mode_merger.py
MolNotator/molnet.py
MolNotator/sample_slicer.py
MolNotator/others/__init__.py
MolNotator/others/duplicate_finder.py
MolNotator/others/fragnotator_edge_table.py
MolNotator/others/global_functions.py
MolNotator/others/reindexer.py
MolNotator/others/rt_slicer.py
MolNotator/others/singleton_edges.py
MolNotator/others/species_validators.py
MolNotator/others/spectrum_extractor.py
MolNotator-0.1.2.dist-info/LICENCE
MolNotator-0.1.2.dist-info/METADATA
MolNotator-0.1.2.dist-info/WHEEL
MolNotator-0.1.2.dist-info/top_level.txt
MolNotator-0.1.2.dist-info/RECORD
