Metadata-Version: 2.1
Name: MolNotator
Version: 0.1.2
Summary: Predict the actual molecules in LC-MS/MS data through an interpretation of the ions detected via combinatorial triangulation.
Home-page: https://github.com/ZzakB/MolNotator
Author: Damien Olivier-Jimenez, Zakaria Bouchouireb
Author-email: damien.olivier.jimenez@gmail.com, zakaria.bouchouireb@univ-nantes.fr
License: MIT
Classifier: Development Status :: 4 - Beta
Classifier: Environment :: Console
Classifier: Intended Audience :: Science/Research
Classifier: License :: OSI Approved :: MIT License
Classifier: Operating System :: POSIX :: Linux
Classifier: Programming Language :: Python
Classifier: Programming Language :: Python :: 3.7
Classifier: Topic :: Scientific/Engineering :: Chemistry
Requires-Python: >=3.7
License-File: LICENCE
